{"apps_id": 54516, "name": "Paralympic - Showdown", "summary": "The Showdown game content is designed to help you play the Paralympic sport of Showdown in virtual reality. The content is designed to help you familiarize yourself with the rules of Showdown and improve your skills through repeated practice.", "app_banner": "https://cdn.sidequestvr.com/file/3906068/1_2560x1440-trailor_socialvalue_ver-001.png", "image_url": "https://cdn.sidequestvr.com/file/3906067/1_2560x1440-trailor_socialvalue_ver-001.png", "is_webxr": false, "versioncode": 3, "is_seated": false, "packagename": "com.ContentsDa.ParalympicsShowdown", "ab_enable": false, "labrador_url": "https://www.meta.com/experiences/paralympic-showdown/9773509666028472/", "supports_go": false, "supports_quest": true, "supports_pico": false, "supports_magic_leap": false, "supports_link": false, "early_access": false, "created": "1774095777753", "license": "PAID", "rating": "5.0000000000000000", "number_of_rating": "1", "downloads": "1", "oculus_auto_generated": false, "oculus_auto_generated_creator": null, "is_multi_url": false, "disable_reviews": false, "is_sidelined": false, "release_channels_enabled": false}